complexplorer/__init__.py
complexplorer/_version.py
complexplorer/api.py
complexplorer/exceptions.py
complexplorer/special.py
complexplorer/core/__init__.py
complexplorer/core/color_utils.py
complexplorer/core/colormap.py
complexplorer/core/constants.py
complexplorer/core/domain.py
complexplorer/core/functions.py
complexplorer/core/scaling.py
complexplorer/export/__init__.py
complexplorer/export/stl/__init__.py
complexplorer/export/stl/mesh_repair.py
complexplorer/export/stl/ornament_generator.py
complexplorer/export/stl/utils.py
complexplorer/plotting/__init__.py
complexplorer/plotting/validation.py
complexplorer/plotting/matplotlib/__init__.py
complexplorer/plotting/matplotlib/plot_2d.py
complexplorer/plotting/matplotlib/plot_3d.py
complexplorer/plotting/pyvista/__init__.py
complexplorer/plotting/pyvista/plot_3d.py
complexplorer/plotting/pyvista/riemann.py
complexplorer/plotting/pyvista/utils.py
complexplorer/utils/__init__.py
complexplorer/utils/backend.py
complexplorer/utils/color.py
complexplorer/utils/logging.py
complexplorer/utils/mesh.py
complexplorer/utils/mesh_distortion.py
complexplorer/utils/validation.py
complexplorer-2.0.0.dist-info/licenses/LICENSE
complexplorer-2.0.0.dist-info/licenses/LICENSE.art
complexplorer-2.0.0.dist-info/METADATA
complexplorer-2.0.0.dist-info/WHEEL
complexplorer-2.0.0.dist-info/top_level.txt
complexplorer-2.0.0.dist-info/RECORD
