Metadata-Version: 2.4
Name: complexplorer
Version: 2.0.0
Summary: Complex function visualizations inspired by Elias Wegert's 'Visual Complex Functions - An Introduction with Phase Portraits'
Author-email: Igor Kuvychko <igor.kuvychko@gmail.com>
Project-URL: Homepage, https://github.com/kuvychko/complexplorer
Project-URL: Bug Tracker, https://github.com/kuvychko/complexplorer/issues
Classifier: Intended Audience :: Science/Research
Classifier: Programming Language :: Python :: 3.11
Classifier: Programming Language :: Python :: 3.12
Classifier: Programming Language :: Python :: 3.13
Classifier: License :: OSI Approved :: BSD License
Classifier: Topic :: Scientific/Engineering :: Visualization
Classifier: Topic :: Multimedia :: Graphics
Classifier: Operating System :: OS Independent
Classifier: Framework :: Matplotlib
Requires-Python: >=3.11
License-File: LICENSE
License-File: LICENSE.art
Requires-Dist: numpy>=1.26.0
Requires-Dist: matplotlib>=3.8.0
Requires-Dist: scipy>=1.11.0
Provides-Extra: dev
Requires-Dist: pytest>=7.0.0; extra == "dev"
Requires-Dist: pytest-cov>=3.0.0; extra == "dev"
Requires-Dist: pytest-timeout>=2.1.0; extra == "dev"
Provides-Extra: pyvista
Requires-Dist: pyvista>=0.45.0; extra == "pyvista"
Provides-Extra: qt
Requires-Dist: PyQt6>=6.5.0; extra == "qt"
Provides-Extra: all
Requires-Dist: complexplorer[dev,pyvista,qt]; extra == "all"
Dynamic: license-file
